<annotation>
	<folder>self-images</folder>
	<filename>20210902_10_14_10_639_000_cfPvBNAyiMOANxwdSiC998X707o2_F_3000_4000.jpg</filename>
	<path>D:\bs\yolov9-main\data\mydata\self-images\20210902_10_14_10_639_000_cfPvBNAyiMOANxwdSiC998X707o2_F_3000_4000.jpg</path>
	<source>
		<database>Unknown</database>
	</source>
	<size>
		<width>3000</width>
		<height>4000</height>
		<depth>3</depth>
	</size>
	<segmented>0</segmented>
	<object>
		<name>1</name>
		<pose>Unspecified</pose>
		<truncated>0</truncated>
		<difficult>0</difficult>
		<bndbox>
			<xmin>1102</xmin>
			<ymin>1356</ymin>
			<xmax>1178</xmax>
			<ymax>1608</ymax>
		</bndbox>
	</object>
	<object>
		<name>3</name>
		<pose>Unspecified</pose>
		<truncated>0</truncated>
		<difficult>0</difficult>
		<bndbox>
			<xmin>1198</xmin>
			<ymin>1352</ymin>
			<xmax>1358</xmax>
			<ymax>1664</ymax>
		</bndbox>
	</object>
	<object>
		<name>7</name>
		<pose>Unspecified</pose>
		<truncated>0</truncated>
		<difficult>0</difficult>
		<bndbox>
			<xmin>1406</xmin>
			<ymin>1324</ymin>
			<xmax>1586</xmax>
			<ymax>1588</ymax>
		</bndbox>
	</object>
</annotation>
