<root><folder>self-images</folder>
	<filename>20210811_09_17_43_524_000_rsGisR1i8VXny1ohxxD9oh1Xxhn1_F_3000_4000.jpg</filename>
	<path>data/mydata/images\20210811_09_17_43_524_000_rsGisR1i8VXny1ohxxD9oh1Xxhn1_F_3000_4000transformed3.jpg</path>
	<source>
		<database>Unknown</database>
	</source>
	<size>
		<width>1113</width>
		<height>1485</height>
		<depth>3</depth>
	</size>
	<segmented>0</segmented>
	<object>
		<name>.</name>
		<pose>Unspecified</pose>
		<truncated>0</truncated>
		<difficult>0</difficult>
		<bndbox>
			<xmin>624</xmin>
			<ymin>1045</ymin>
			<xmax>643</xmax>
			<ymax>1085</ymax>
		</bndbox>
	</object>
	<object>
		<name>3</name>
		<pose>Unspecified</pose>
		<truncated>0</truncated>
		<difficult>0</difficult>
		<bndbox>
			<xmin>484</xmin>
			<ymin>907</ymin>
			<xmax>543</xmax>
			<ymax>1087</ymax>
		</bndbox>
	</object>
	<object>
		<name>3</name>
		<pose>Unspecified</pose>
		<truncated>0</truncated>
		<difficult>0</difficult>
		<bndbox>
			<xmin>566</xmin>
			<ymin>905</ymin>
			<xmax>629</xmax>
			<ymax>1075</ymax>
		</bndbox>
	</object>
	<object>
		<name>0</name>
		<pose>Unspecified</pose>
		<truncated>0</truncated>
		<difficult>0</difficult>
		<bndbox>
			<xmin>640</xmin>
			<ymin>913</ymin>
			<xmax>721</xmax>
			<ymax>1072</ymax>
		</bndbox>
	</object>
</root>