<root><folder>self-images</folder>
	<filename>20210831_18_04_08_951_000_KHmDZV1nA9afQm6C1fZ6iGmNRl82_F_4160_3120.jpg</filename>
	<path>data/mydata/images\20210831_18_04_08_951_000_KHmDZV1nA9afQm6C1fZ6iGmNRl82_F_4160_3120transformed2.jpg</path>
	<source>
		<database>Unknown</database>
	</source>
	<size>
		<width>1804</width>
		<height>2405</height>
		<depth>3</depth>
	</size>
	<segmented>0</segmented>
	<object>
		<name>9</name>
		<pose>Unspecified</pose>
		<truncated>0</truncated>
		<difficult>0</difficult>
		<bndbox>
			<xmin>789</xmin>
			<ymin>939</ymin>
			<xmax>881</xmax>
			<ymax>1137</ymax>
		</bndbox>
	</object>
	<object>
		<name>.</name>
		<pose>Unspecified</pose>
		<truncated>0</truncated>
		<difficult>0</difficult>
		<bndbox>
			<xmin>878</xmin>
			<ymin>1100</ymin>
			<xmax>922</xmax>
			<ymax>1141</ymax>
		</bndbox>
	</object>
	<object>
		<name>7</name>
		<pose>Unspecified</pose>
		<truncated>0</truncated>
		<difficult>0</difficult>
		<bndbox>
			<xmin>925</xmin>
			<ymin>925</ymin>
			<xmax>1018</xmax>
			<ymax>1120</ymax>
		</bndbox>
	</object>
</root>